pyrtlsdrlib/__init__.py
pyrtlsdrlib/common.py
pyrtlsdrlib/platform.py
pyrtlsdrlib/lib/__init__.py
pyrtlsdrlib/lib/build-meta.json
pyrtlsdrlib/lib/librtlsdr.0.8git.dylib
pyrtlsdrlib/lib/librtlsdr.0.dylib
pyrtlsdrlib/lib/librtlsdr.dylib
pyrtlsdrlib/lib/custom_build/__init__.py
pyrtlsdrlib/lib/custom_build/build-meta.json
pyrtlsdrlib/lib/custom_build/librtlsdr.0.9git.dylib
pyrtlsdrlib/lib/custom_build/librtlsdr.0.dylib
pyrtlsdrlib/lib/custom_build/librtlsdr.dylib
pyrtlsdrlib-0.0.3.dist-info/LICENSE
pyrtlsdrlib-0.0.3.dist-info/METADATA
pyrtlsdrlib-0.0.3.dist-info/WHEEL
pyrtlsdrlib-0.0.3.dist-info/top_level.txt
pyrtlsdrlib-0.0.3.dist-info/RECORD
